{
  "db_name": "PostgreSQL",
  "query": "\n            insert into todos (text, completed)\n            values ($1, false)\n            returning *\n            ",
  "describe": {
    "columns": [
      {
        "ordinal": 0,
        "name": "id",
        "type_info": "Int4"
      },
      {
        "ordinal": 1,
        "name": "text",
        "type_info": "Text"
      },
      {
        "ordinal": 2,
        "name": "completed",
        "type_info": "Bool"
      }
    ],
    "parameters": {
      "Left": [
        "Text"
      ]
    },
    "nullable": [
      false,
      false,
      false
    ]
  },
  "hash": "39a57d15e577cc030593298be02e19d4b9b87be327cd818a8711a33a12a7da5e"
}
